slack/__init__.py
slack/notify.py
notify_via_slack-0.1.1.dist-info/WHEEL
notify_via_slack-0.1.1.dist-info/METADATA
notify_via_slack-0.1.1.dist-info/RECORD
